fpga/radiant_project/source/impl_1/seven_seg_decoder.sv
/*
	name: Zhian Zhou
	email: zzhou@g.hmc.deu
	date:9/5/2024
*/

module seven_seg_decoder(
    input logic [3:0] s,
    output logic [6:0] seg
);
	
    always_comb begin
        case (s)
			4'b0000: seg = 7'b111_1110; // 0
			4'b0001: seg = 7'b011_0000; // 1
			4'b0010: seg = 7'b110_1101; // 2
			4'b0011: seg = 7'b111_1001; // 3 
			4'b0100: seg = 7'b011_0011; // 4
			4'b0101: seg = 7'b101_1011; // 5
			4'b0110: seg = 7'b101_1111; // 6
			4'b0111: seg = 7'b111_0000; // 7
			4'b1000: seg = 7'b111_1111; // 8
			4'b1001: seg = 7'b111_1011; // 9
			4'b1010: seg = 7'b111_0111; // A
			4'b1011: seg = 7'b001_1111; // b
			4'b1100: seg = 7'b100_1110; // C
			4'b1101: seg = 7'b011_1101; // d
			4'b1110: seg = 7'b100_1111; // E
			4'b1111: seg = 7'b100_0111; // F
			default: seg = 7'b000_0000;
		endcase
	end	
	
endmodule

fpga/src/impl_1/seven_seg_decoder_tb.sv
/*
	name: Zhian Zhou
	email: zzhou@g.hmc.deu
	date:9/5/2024
*/

`timescale 1ns/1ns
`default_nettype none
`define N_TV 8

module seven_seg_decoder_tb();
 // Set up test signals
 logic clk, reset;
 logic [3:0] s;
 logic [6:0] seg, seg_expected;
 logic [31:0] vectornum, errors;
 logic [10:0] testvectors[10000:0]; // Vectors of format s[3:0]_seg[6:0]

 // Instantiate the device under test
 seven_seg_decoder dut(.s(s), .seg(seg));

 // Generate clock signal with a period of 10 timesteps.
 always
   begin
     clk = 1; #5;
     clk = 0; #5;
   end
  
 // At the start of the simulation:
 //  - Load the testvectors
 //  - Pulse the reset line (if applicable)
 initial
   begin
     testvectors[0] = 11'b0000_111_1110; // 0
	 testvectors[1] = 11'b0001_011_0000; // 1
	 testvectors[2] = 11'b0010_110_1101; // 2
	 testvectors[3] = 11'b0011_111_1001; // 3 
	 testvectors[4] = 11'b0100_011_0011; // 4
	 testvectors[5] = 11'b0101_101_1011; // 5
	 testvectors[6] = 11'b0110_101_1111; // 6
	 testvectors[7] = 11'b0111_111_0000; // 7
	 testvectors[8] = 11'b1000_111_1111; // 8
	 testvectors[9] = 11'b1001_111_1011; // 9
	 testvectors[10] = 11'b1010_111_0111; // A
	 testvectors[11] = 11'b1011_001_1111; // b
	 testvectors[12] = 11'b1100_100_1110; // C
	 testvectors[13] = 11'b1101_011_1101; // d
	 testvectors[14] = 11'b1110_100_1111; // E
	 testvectors[15] = 11'b1111_100_0111; // F
     vectornum = 0; errors = 0;
     reset = 1; #27; reset = 0;
   end
  // Apply test vector on the rising edge of clk
 always @(posedge clk)
   begin
       #1; {s, seg_expected} = testvectors[vectornum];
   end
  initial
 begin
   // Create dumpfile for signals
   $dumpfile("seven_seg_decoder_tb.vcd");
   $dumpvars(0, seven_seg_decoder_tb);
 end
  // Check results on the falling edge of clk
 always @(negedge clk)
   begin
     if (~reset) // skip during reset
       begin
         if (seg != seg_expected)
           begin
             $display("Error: inputs: s=%b", s);
             $display(" outputs: seg=%b (%b expected)", seg, seg_expected);
             errors = errors + 1;
           end

      
       vectornum = vectornum + 1;
      
       if (testvectors[vectornum] === 11'bx)
         begin
           $display("%d tests completed with %d errors.", vectornum, errors);
           $finish;
         end
     end
   end
endmodule

fpga/radiant_project/seven_seg_decoder_tb.vcd
$date
	Tue Sep 24 15:38:28 2024
$end
$version
	Questa Lattice OEM Edition 2024.2
$end
$timescale
	1ns
$end

$scope module seven_seg_decoder_tb $end
$var reg 1 ! clk $end
$var reg 1 " reset $end
$var reg 4 # s [3:0] $end
$var reg 7 $ seg [6:0] $end
$var reg 7 % seg_expected [6:0] $end
$var reg 32 & vectornum [31:0] $end
$var reg 32 ' errors [31:0] $end

$scope module dut $end
$var wire 1 ( s [3] $end
$var wire 1 ) s [2] $end
$var wire 1 * s [1] $end
$var wire 1 + s [0] $end
$var reg 7 , seg [6:0] $end
$upscope $end
$upscope $end
$enddefinitions $end
#0
$dumpvars
1!
1"
bx #
b0 $
bx %
b0 &
b0 '
b0 ,
x+
x*
x)
x(
$end
#1
b1111110 %
b0 #
0+
0*
0)
0(
b1111110 ,
b1111110 $
#5
0!
#10
1!
#15
0!
#20
1!
#25
0!
#27
0"
#30
1!
#35
0!
b1 &
#40
1!
#41
b110000 %
b1 #
1+
b110000 ,
b110000 $
#45
0!
b10 &
#50
1!
#51
b1101101 %
b10 #
0+
1*
b1101101 ,
b1101101 $
#55
0!
b11 &
#60
1!
#61
b1111001 %
b11 #
1+
b1111001 ,
b1111001 $
#65
0!
b100 &
#70
1!
#71
b110011 %
b100 #
0+
0*
1)
b110011 ,
b110011 $
#75
0!
b101 &
#80
1!
#81
b1011011 %
b101 #
1+
b1011011 ,
b1011011 $
#85
0!
b110 &
#90
1!
#91
b1011111 %
b110 #
0+
1*
b1011111 ,
b1011111 $
#95
0!
b111 &
#100
1!
#101
b1110000 %
b111 #
1+
b1110000 ,
b1110000 $
#105
0!
b1000 &
#110
1!
#111
b1111111 %
b1000 #
0+
0*
0)
1(
b1111111 ,
b1111111 $
#115
0!
b1001 &
#120
1!
#121
b1111011 %
b1001 #
1+
b1111011 ,
b1111011 $
#125
0!
b1010 &
#130
1!
#131
b1110111 %
b1010 #
0+
1*
b1110111 ,
b1110111 $
#135
0!
b1011 &
#140
1!
#141
b11111 %
b1011 #
1+
b11111 ,
b11111 $
#145
0!
b1100 &
#150
1!
#151
b1001110 %
b1100 #
0+
0*
1)
b1001110 ,
b1001110 $
#155
0!
b1101 &
#160
1!
#161
b111101 %
b1101 #
1+
b111101 ,
b111101 $
#165
0!
b1110 &
#170
1!
#171
b1001111 %
b1110 #
0+
1*
b1001111 ,
b1001111 $
#175
0!
b1111 &
#180
1!
#181
b1000111 %
b1111 #
1+
b1000111 ,
b1000111 $
#185
0!
b10000 &
